diffpdf/__init__.py
diffpdf/cli.py
diffpdf/hash_check.py
diffpdf/logger.py
diffpdf/page_check.py
diffpdf/py.typed
diffpdf/text_check.py
diffpdf/visual_check.py
diffpdf-1.1.1.dist-info/METADATA
diffpdf-1.1.1.dist-info/WHEEL
diffpdf-1.1.1.dist-info/entry_points.txt
diffpdf-1.1.1.dist-info/licenses/LICENSE
diffpdf-1.1.1.dist-info/RECORD
