Metadata-Version: 2.4
Name: diffpdf
Version: 1.1.1
Summary: A tool for comparing PDF files
Project-URL: Homepage, https://github.com/JustusRijke/DiffPDF
Project-URL: Issues, https://github.com/JustusRijke/DiffPDF/issues
Author-email: Justus Rijke <justusrijke@gmail.com>
License-Expression: MIT
License-File: LICENSE
Classifier: Development Status :: 5 - Production/Stable
Classifier: Operating System :: Microsoft :: Windows
Classifier: Operating System :: POSIX :: Linux
Classifier: Programming Language :: Python :: 3
Classifier: Typing :: Typed
Requires-Python: >=3.10.0
Requires-Dist: click>=8
Requires-Dist: pillow>=10.0.0
Requires-Dist: pixelmatch-fast>=1.3.1
Requires-Dist: pre-commit>=4.5.1
Requires-Dist: pymupdf>=1.23.0
